django_thumbor/__init__.py
django_thumbor/conf.py
django_thumbor/templatetags/__init__.py
django_thumbor/templatetags/thumbor_tags.py
django_thumbor-0.6.0.dist-info/LICENSE
django_thumbor-0.6.0.dist-info/METADATA
django_thumbor-0.6.0.dist-info/WHEEL
django_thumbor-0.6.0.dist-info/top_level.txt
django_thumbor-0.6.0.dist-info/RECORD
