Metadata-Version: 2.1
Name: django-thumbor
Version: 0.6.0
Summary: A django application to resize images using the thumbor service
Home-page: http://github.com/ricobl/django-thumbor/
Author: Enrico Batista da Luz
Author-email: rico.bl@gmail.com
License: django-thumbor is licensed under the MIT license. For more information, please see LICENSE file.
Classifier: License :: OSI Approved :: MIT License
License-File: LICENSE
Requires-Dist: Django >=1.4
Requires-Dist: libthumbor >=1.2.0
